pycppjson/__init__.py
pycppjson/dumper.py
pycppjson/loader.py
pycppjson-1.0.dist-info/LICENSE
pycppjson-1.0.dist-info/METADATA
pycppjson-1.0.dist-info/WHEEL
pycppjson-1.0.dist-info/top_level.txt
pycppjson-1.0.dist-info/RECORD
