Metadata-Version: 2.1
Name: pycppjson
Version: 1.0
Summary: Cpp JSON wrapper
License-File: LICENSE
